{
    "type": "pi0",
    "n_obs_steps": 1,
    "device": "cpu",
    "use_amp": true,
    "normalization_mapping": {
        "VISUAL": "IDENTITY",
        "STATE": "IDENTITY",
        "ACTION": "IDENTITY"
    },
    "input_features": {
        "observation.images.top": {
          "shape": [
            3,
            224,
            224
          ],
          "type": "VISUAL"
        },
        "observation.state": {
          "shape": [
            8
          ],
          "type": "STATE"
        }
    },
    "output_features": {
        "action": {
            "type": "ACTION",
            "shape": [
                7
            ]
        }
    },
    "chunk_size": 4,
    "n_action_steps": 4,
    "max_state_dim": 8,
    "max_action_dim": 7,
    "resize_imgs_with_padding": [
        224,
        224
    ],
    "empty_cameras": 0,
    "adapt_to_pi_aloha": false,
    "use_delta_joint_actions_aloha": false,
    "tokenizer_max_length": 72,
    "proj_width": 1024,
    "num_steps": 10,
    "use_cache": true,
    "attention_implementation": "eager",
    "freeze_vision_encoder": false,
    "train_expert_only": false,
    "train_state_proj": true,
    "optimizer_lr": 5e-5,
    "optimizer_betas": [
        0.9,
        0.999
    ],
    "optimizer_eps": 1e-8,
    "optimizer_weight_decay": 0,
    "scheduler_warmup_steps": 200,
    "scheduler_decay_steps": 30000,
    "scheduler_decay_lr": 2.5e-06
}